{"inkVersion":21,"root":[["^Good job! Ngayon, i-review natin muli ang lahat ng iyong natutunan. ","#","^speaker: Teacher","/#","\n","^Hindi natin matatakasan ang stress, kaya kailangan matuto ka sa mga healthy na paraan ng pagcope ng stress. ","#","^speaker: Teacher","/#","\n","^Ang pagcope ng stess ay maaring gawin sa pamamagitan ng mindful breathing, o sa pamamagitan ng pagsunod sa Bilog ng Buhay. ","#","^speaker: Teacher","/#","\n","^Ang Bilog ng Buhay ay may apat na bahagi: Kapwa, Kabuluhan, Kalooban at Kakayanan. ","#","^speaker: Teacher","/#","\n","^Sa pamamagitan ng pag-alala kung paano gumamit ng mindful breathing at ang Bilog ng Buhay, mula ngayon dapat handan ka na i-manage ang iyong stress! ","#","^speaker: Teacher","/#","\n","end",["done",{"#f":5,"#n":"g-0"}],null],"done",{"#f":1}],"listDefs":{}}